Metadata-Version: 2.1
Name: ChordScaleWizard
Version: 1.0.0
Summary: A Python package for getting music notes of chords and scales.
Home-page: https://github.com/Arianshh/ChordScaleWizard
Author: Arian Shariat
Author-email: arian.shariat@gmail.com
License: MIT
Keywords: music notes chords scale
Classifier: Development Status :: 3 - Alpha
Classifier: Intended Audience :: Developers
Classifier: License :: OSI Approved :: MIT License
Classifier: Programming Language :: Python :: 3
Classifier: Programming Language :: Python :: 3.6
Classifier: Programming Language :: Python :: 3.7
Classifier: Programming Language :: Python :: 3.8
Classifier: Programming Language :: Python :: 3.9
